{"coordinateSystem":"origin at room center; +x right, +z toward front wall, +y up","followAgentId":null,"cameraTarget":{"x":0,"y":0,"z":0},"agents":[{"agentId":"sim-alpha-1770857436459","name":"Sim Alpha","x":113.02,"y":0,"z":71.55},{"agentId":"sim-bravo-1770857436459","name":"Sim Bravo","x":-18.77,"y":0,"z":21.13},{"agentId":"sim-charlie-1770857436459","name":"Sim Charlie","x":168,"y":0,"z":26.18}],"activeBattles":[],"recentChat":["[BATTLE] sim-bravo-1770857436459 locked intent: strike (turn 2).","[BATTLE] Turn 2: sim-alpha-1770857436459(guard) -> 0 dmg, sim-bravo-1770857436459(strike) -> 10 dmg. HP sim-alpha-1770857436459:76 sim-bravo-1770857436459:72","[BATTLE] sim-alpha-1770857436459 locked intent: retreat (turn 3).","[BATTLE] sim-bravo-1770857436459 locked intent: strike (turn 3).","[BATTLE] Turn 3: sim-alpha-1770857436459(retreat) -> 0 dmg, sim-bravo-1770857436459(strike) -> 30 dmg. HP sim-alpha-1770857436459:46 sim-bravo-1770857436459:72","[BATTLE] sim-alpha-1770857436459 retreated. sim-bravo-1770857436459 wins."]}